[
 {"formId":"0x00027668", "id":"0"}
,{"formId":"0x0001DC4D", "id":"1"}
,{"formId":"0x0001DC4C", "id":"2"}
,{"formId":"0x00025B39", "id":"3"}
,{"formId":"0x000164C4", "id":"4"}
,{"formId":"0x000164CA", "id":"5"}
,{"formId":"0x00017690", "id":"6"}
,{"formId":"0x00017696", "id":"7"}
,{"formId":"0x0001769C", "id":"8"}
,{"formId":"0x000176A3", "id":"9"}
,{"formId":"0x000176A9", "id":"10"}
,{"formId":"0x000176AF", "id":"11"}
,{"formId":"0x000176B5", "id":"12"}
,{"formId":"0x000176B8", "id":"13"}
,{"formId":"0x00017832", "id":"14"}
,{"formId":"0x0001C0CB", "id":"15"}
,{"formId":"0x0001C0D1", "id":"16"}
,{"formId":"0x0001C0D7", "id":"17"}
,{"formId":"0x0001C0DD", "id":"18"}
,{"formId":"0x000176BE", "id":"19"}
,{"formId":"0x000176C4", "id":"20"}
,{"formId":"0x0003B1DD", "id":"21"}
,{"formId":"0x0003B1DE", "id":"22"}
]