[
  {"id": 1,"formId": "0x000243CD"},
  {"id": 2,"formId": "0x000243CB"},
  {"id": 3,"formId": "0x000243CC"},
  {"id": 4,"formId": "0x000243CE"},
  {"id": 5,"formId": "0x000243CA"},
  {"id": 6,"formId": "0x00073A5F"},
  {"id": 7,"formId": "0x000243D2"},
  {"id": 8,"formId": "0x000243CF"},
  {"id": 9,"formId": "0x000243D0"},
  {"id": 10,"formId": "0x000243D1"},
  {"id": 11,"formId": "0x000243D4"},
  {"id": 12,"formId": "0x000243D5"},
  {"id": 13,"formId": "0x000243D8"},
  {"id": 14,"formId": "0x00073A69"},
  {"id": 15,"formId": "0x000243D6"},
  {"id": 16,"formId": "0x000243D9"},
  {"id": 17,"formId": "0x000243DC"},
  {"id": 18,"formId": "0x00073A68"},
  {"id": 19,"formId": "0x000243DA"},
  {"id": 20,"formId": "0x00073A67"},
  {"id": 21,"formId": "0x000243E2"},
  {"id": 22,"formId": "0x000243E1"},
  {"id": 23,"formId": "0x000243DF"},
  {"id": 24,"formId": "0x000243DE"},
  {"id": 25,"formId": "0x000243E0"},
  {"id": 26,"formId": "0x000243E4"},
  {"id": 27,"formId": "0x00073A61"},
  {"id": 28,"formId": "0x000243E5"},
  {"id": 29,"formId": "0x000243E6"},
  {"id": 30,"formId": "0x000243E3"},
  {"id": 31,"formId": "0x000243EA"},
  {"id": 32,"formId": "0x000243E8"},
  {"id": 33,"formId": "0x000243E9"},
  {"id": 34,"formId": "0x000243EC"},
  {"id": 35,"formId": "0x000243EB"},
  {"id": 36,"formId": "0x000243EE"},
  {"id": 37,"formId": "0x000243F0"},
  {"id": 38,"formId": "0x00073A62"},
  {"id": 39,"formId": "0x00073A66"},
  {"id": 40,"formId": "0x000243EF"},
  {"id": 41,"formId": "0x000243F5"},
  {"id": 42,"formId": "0x000243F4"},
  {"id": 43,"formId": "0x000243F2"},
  {"id": 44,"formId": "0x00073A60"},
  {"id": 45,"formId": "0x00022B04"},
  {"id": 46,"formId": "0x000243F6"},
  {"id": 47,"formId": "0x000243FA"},
  {"id": 48,"formId": "0x000243F7"},
  {"id": 49,"formId": "0x000243F9"},
  {"id": 50,"formId": "0x000243FB"},
  {"id": 51,"formId": "0x00022B05"},
  {"id": 52,"formId": "0x000243F8"},
  {"id": 53,"formId": "0x000243FE"},
  {"id": 54,"formId": "0x000243FC"},
  {"id": 55,"formId": "0x00024400"},
  {"id": 56,"formId": "0x00073A6A"},
  {"id": 57,"formId": "0x000243FD"},
  {"id": 58,"formId": "0x00024402"},
  {"id": 59,"formId": "0x00024403"},
  {"id": 60,"formId": "0x000A915C"},
  {"id": 61,"formId": "0x00024401"},
  {"id": 62,"formId": "0x00024405"},
  {"id": 63,"formId": "0x00024404"},
  {"id": 64,"formId": "0x00024407"},
  {"id": 65,"formId": "0x00024408"},
  {"id": 66,"formId": "0x0002440A"},
  {"id": 67,"formId": "0x00022B06"},
  {"id": 68,"formId": "0x00024409"},
  {"id": 69,"formId": "0x00024406"},
  {"id": 70,"formId": "0x0002440C"},
  {"id": 71,"formId": "0x0002440D"},
  {"id": 72,"formId": "0x0002440B"},
  {"id": 73,"formId": "0x0002440E"},
  {"id": 74,"formId": "0x0002440F"},
  {"id": 75,"formId": "0x00024531"},
  {"id": 76,"formId": "0x00024411"},
  {"id": 77,"formId": "0x00024530"},
  {"id": 78,"formId": "0x00024410"},
  {"id": 79,"formId": "0x0002452F"},
  {"id": 80,"formId": "0x00024534"},
  {"id": 81,"formId": "0x00024532"},
  {"id": 82,"formId": "0x00024535"},
  {"id": 83,"formId": "0x00024536"},
  {"id": 84,"formId": "0x00024533"},
  {"id": 85,"formId": "0x00024538"},
  {"id": 86,"formId": "0x00073A63"},
  {"id": 87,"formId": "0x00024539"},
  {"id": 88,"formId": "0x00024537"},
  {"id": 89,"formId": "0x00022B07"},
  {"id": 90,"formId": "0x00073A6B"},
  {"id": 91,"formId": "0x0002453F"},
  {"id": 92,"formId": "0x0002453E"},
  {"id": 93,"formId": "0x00024540"},
  {"id": 94,"formId": "0x0002453D"},
  {"id": 95,"formId": "0x0002453C"},
  {"id": 96,"formId": "0x00073A65"},
  {"id": 97,"formId": "0x00024541"},
  {"id": 98,"formId": "0x00073A64"},
  {"id": 99,"formId": "0x00024545"},
  {"id": 100,"formId": "0x00024542"},
  {"id": 101,"formId": "0x00024547"},
  {"id": 102,"formId": "0x00024549"},
  {"id": 103,"formId": "0x0002454A"},
  {"id": 104,"formId": "0x00024548"},
  {"id": 105,"formId": "0x00024546"},
  {"id": 106,"formId": "0x0002454D"},
  {"id": 107,"formId": "0x0002454B"},
  {"id": 108,"formId": "0x0002454C"},
  {"id": 109,"formId": "0x0002454E"}
]